{
    "Date and Time": "2025-08-18_15_58",
    "Comments": "Testing the second PA. Concerned the tolerance on the capacitors is effecting the operation of the PA",
    "Configuration": {
        "Frequency": [
            8,
            8.5,
            9,
            9.5,
            10,
            10.5,
            11,
            11.5,
            12
        ],
        "Sweep Type": "Gamma",
        "Set Power (dBm)": [
            10,
            11,
            12,
            13,
            14,
            15,
            16,
            17,
            18,
            19,
            20,
            20.25,
            20.5,
            20.75,
            21,
            21.25,
            21.5,
            21.75,
            22,
            22.25,
            22.5,
            22.75,
            23,
            23.25,
            23.5,
            23.75,
            24,
            24.25,
            24.5,
            24.75,
            25
        ],
        "Set Power Plane": "DUT input",
        "Gamma Magnitude List": [
            0
        ],
        "Gamma Phase List": [
            0
        ],
        "Rectangular Offset [x,y]": [
            0,
            0
        ],
        "Real Impedance List": [],
        "Imaginary Impedance List": [],
        "Gate Bias Voltages": [
            1.8,
            1.7,
            1.6,
            1.5
        ],
        "PNA": {
            "Address": "Defined in script GPIB",
            "Input port": "1",
            "Output port": "2"
        },
        "Load Tuner": {
            "Tuner SN": "3002",
            "Timeout": 1000,
            "Port": 5030,
            "Print Statements": 0,
            "Tuner Calibration File": "C:\\Users\\grgo8200\\Documents\\AFRL_Testbench\\data\\tunercal\\MT982AU06_3002.tunx"
        },
        "Files": {
            "IL Freqs": [
                8,
                8.1,
                8.2,
                8.3,
                8.4,
                8.5,
                8.6,
                8.7,
                8.8,
                8.9,
                9,
                9.1,
                9.2,
                9.3,
                9.4,
                9.5,
                9.6,
                9.7,
                9.8,
                9.9,
                10,
                10.1,
                10.2,
                10.3,
                10.4,
                10.5,
                10.6,
                10.7,
                10.8,
                10.9,
                11,
                11.1,
                11.2,
                11.3,
                11.4,
                11.5,
                11.6,
                11.7,
                11.8,
                11.9,
                12
            ],
            "Output Sparam IL (dB)": "C:/Users/grgo8200/Documents/GitHub/summer2025_loadpull_repo/data/deembedsparam/DUT2pm_output",
            "Input Sparam IL (dB)": "C:/Users/grgo8200/Documents/GitHub/summer2025_loadpull_repo/data/deembedsparam/DUT2pm_input",
            "Thru Sparam IL (dB)": "C:/Users/grgo8200/Documents/GitHub/summer2025_loadpull_repo/data/deembedsparam/DUTThru",
            "Output Coupling (dB)": "C:/Users/grgo8200/Documents/GitHub/summer2025_loadpull_repo/data/deembedatten/2025-07-28_23_39_Freq12.0to8.0/pna2dut_output",
            "Input Coupling (dB)": "C:/Users/grgo8200/Documents/GitHub/summer2025_loadpull_repo/data/deembedatten/2025-07-28_23_39_Freq12.0to8.0/pna2dut_input"
        },
        "Samplers": {
            "Bias": [
                1.25
            ],
            "1": {
                "DMM Address": "GPIB1::22::INSTR",
                "Filter Number": ""
            },
            "2": {
                "DMM Address": "GPIB1::28::INSTR",
                "Filter Number": ""
            }
        },
        "DC Supply": {
            "Address": "USB1::0x05E6::0x2230::9032546::0::INSTR",
            "Gate Channel": 3,
            "Drain Channel": 2,
            "Sampler Bias Channel": 1
        }
    },
    "Load Point: 10.0_0j_0": {
        "load_gamma": {
            "real": 0.0,
            "imag": 0.0
        },
        "wave data": {
            "input_awave": {
                "trace_name": "input_awave_trace",
                "x": 67000000000.0,
                "y_real": [
                    -0.05490204
                ],
                "y_imag": [
                    -0.00973388
                ],
                "dBm_mag": [
                    -25.07382
                ]
            },
            "output_awave": {
                "trace_name": "output_awave_trace",
                "x": 67000000000.0,
                "y_real": [
                    0.001718716
                ],
                "y_imag": [
                    -0.003037287
                ],
                "dBm_mag": [
                    -49.14385
                ]
            },
            "input_bwave": {
                "trace_name": "input_bwave_trace",
                "x": 67000000000.0,
                "y_real": [
                    -0.102763
                ],
                "y_imag": [
                    -0.05451656
                ],
                "dBm_mag": [
                    -18.68629
                ]
            },
            "output_bwave": {
                "trace_name": "output_bwave_trace",
                "x": 67000000000.0,
                "y_real": [
                    -0.4441171
                ],
                "y_imag": [
                    0.6733139
                ],
                "dBm_mag": [
                    -1.866916
                ]
            }
        },
        "Power Meter": -61.9574967,
        "Input Power": -17.1262673869,
        "Samplers": {
            "1": 6.5243478e-06,
            "2": 6.79026141e-06,
            "Bias": 0.000589371,
            "Bias Current": 0.0
        },
        "PA Performance": {
            "Gain": 9.64271258146361,
            "PAE": 6.370429241435282,
            "DC Power": 1.28848858698
        },
        "DC Parameters": {
            "gate current": 0.0,
            "gate voltage": 1.79993,
            "drain current": 0.0460186,
            "drain voltage": 27.9993
        }
    },
    "Load Point: 11.0_0j_0": {
        "load_gamma": {
            "real": 0.0,
            "imag": 0.0
        },
        "wave data": {
            "input_awave": {
                "trace_name": "input_awave_trace",
                "x": 67000000000.0,
                "y_real": [
                    0.05534523
                ],
                "y_imag": [
                    -0.02914599
                ],
                "dBm_mag": [
                    -24.07537
                ]
            },
            "output_awave": {
                "trace_name": "output_awave_trace",
                "x": 67000000000.0,
                "y_real": [
                    0.0005361418
                ],
                "y_imag": [
                    0.003832533
                ],
                "dBm_mag": [
                    -48.24611
                ]
            },
            "input_bwave": {
                "trace_name": "input_bwave_trace",
                "x": 67000000000.0,
                "y_real": [
                    0.1300264
                ],
                "y_imag": [
                    -0.02188232
                ],
                "dBm_mag": [
                    -17.59808
                ]
            },
            "output_bwave": {
                "trace_name": "output_bwave_trace",
                "x": 67000000000.0,
                "y_real": [
                    -0.06559185
                ],
                "y_imag": [
                    -0.8878703
                ],
                "dBm_mag": [
                    -1.009372
                ]
            }
        },
        "Power Meter": -58.0330245,
        "Input Power": -16.123568096,
        "Samplers": {
            "1": 6.73187709e-06,
            "2": 6.84375248e-06,
            "Bias": 0.000589371,
            "Bias Current": 0.0
        },
        "PA Performance": {
            "Gain": 9.501806581463608,
            "PAE": 7.356779297990299,
            "DC Power": 1.35384225912
        },
        "DC Parameters": {
            "gate current": 0.0,
            "gate voltage": 1.79991,
            "drain current": 0.0483522,
            "drain voltage": 27.9996
        }
    },
    "Load Point: 12.0_0j_0": {
        "load_gamma": {
            "real": 0.0,
            "imag": 0.0
        },
        "wave data": {
            "input_awave": {
                "trace_name": "input_awave_trace",
                "x": 67000000000.0,
                "y_real": [
                    0.07001598
                ],
                "y_imag": [
                    0.004332325
                ],
                "dBm_mag": [
                    -23.07946
                ]
            },
            "output_awave": {
                "trace_name": "output_awave_trace",
                "x": 67000000000.0,
                "y_real": [
                    -0.001725928
                ],
                "y_imag": [
                    0.00391872
                ],
                "dBm_mag": [
                    -47.36715
                ]
            },
            "input_bwave": {
                "trace_name": "input_bwave_trace",
                "x": 67000000000.0,
                "y_real": [
                    0.1385097
                ],
                "y_imag": [
                    0.05603579
                ],
                "dBm_mag": [
                    -16.51209
                ]
            },
            "output_bwave": {
                "trace_name": "output_bwave_trace",
                "x": 67000000000.0,
                "y_real": [
                    0.4503578
                ],
                "y_imag": [
                    -0.8735912
                ],
                "dBm_mag": [
                    -0.150302
                ]
            }
        },
        "Power Meter": -54.3086238,
        "Input Power": -15.1212188051,
        "Samplers": {
            "1": 6.40914628e-06,
            "2": 6.93388354e-06,
            "Bias": 0.000555992,
            "Bias Current": 0.0
        },
        "PA Performance": {
            "Gain": 9.364966581463609,
            "PAE": 8.445991649061236,
            "DC Power": 1.43137181481
        },
        "DC Parameters": {
            "gate current": 0.0,
            "gate voltage": 1.7999,
            "drain current": 0.0511217,
            "drain voltage": 27.9993
        }
    },
    "Load Point: 13.0_0j_0": {
        "load_gamma": {
            "real": 0.0,
            "imag": 0.0
        },
        "wave data": {
            "input_awave": {
                "trace_name": "input_awave_trace",
                "x": 67000000000.0,
                "y_real": [
                    -0.05668431
                ],
                "y_imag": [
                    -0.05452843
                ],
                "dBm_mag": [
                    -22.08558
                ]
            },
            "output_awave": {
                "trace_name": "output_awave_trace",
                "x": 67000000000.0,
                "y_real": [
                    0.004262661
                ],
                "y_imag": [
                    -0.002046905
                ],
                "dBm_mag": [
                    -46.50526
                ]
            },
            "input_bwave": {
                "trace_name": "input_bwave_trace",
                "x": 67000000000.0,
                "y_real": [
                    -0.07803433
                ],
                "y_imag": [
                    -0.150591
                ],
                "dBm_mag": [
                    -15.41105
                ]
            },
            "output_bwave": {
                "trace_name": "output_bwave_trace",
                "x": 67000000000.0,
                "y_real": [
                    -1.002713
                ],
                "y_imag": [
                    0.4092076
                ],
                "dBm_mag": [
                    0.6925528
                ]
            }
        },
        "Power Meter": -61.0060194,
        "Input Power": -14.1125095142,
        "Samplers": {
            "1": 6.67322147e-06,
            "2": 7.12379069e-06,
            "Bias": 0.000618935,
            "Bias Current": 0.0
        },
        "PA Performance": {
            "Gain": 9.21394138146361,
            "PAE": 9.574636064406109,
            "DC Power": 1.5259840996400003
        },
        "DC Parameters": {
            "gate current": 0.0,
            "gate voltage": 1.79992,
            "drain current": 0.0545006,
            "drain voltage": 27.9994
        }
    },
    "Load Point: 14.0_0j_0": {
        "load_gamma": {
            "real": 0.0,
            "imag": 0.0
        },
        "wave data": {
            "input_awave": {
                "trace_name": "input_awave_trace",
                "x": 67000000000.0,
                "y_real": [
                    -0.03872271
                ],
                "y_imag": [
                    0.07919679
                ],
                "dBm_mag": [
                    -21.09491
                ]
            },
            "output_awave": {
                "trace_name": "output_awave_trace",
                "x": 67000000000.0,
                "y_real": [
                    -0.003566083
                ],
                "y_imag": [
                    -0.003788081
                ],
                "dBm_mag": [
                    -45.67568
                ]
            },
            "input_bwave": {
                "trace_name": "input_bwave_trace",
                "x": 67000000000.0,
                "y_real": [
                    -0.1362288
                ],
                "y_imag": [
                    0.1354859
                ],
                "dBm_mag": [
                    -14.32801
                ]
            },
            "output_bwave": {
                "trace_name": "output_bwave_trace",
                "x": 67000000000.0,
                "y_real": [
                    0.7634225
                ],
                "y_imag": [
                    0.9151461
                ],
                "dBm_mag": [
                    1.52382
                ]
            }
        },
        "Power Meter": -57.6574935,
        "Input Power": -13.1013302233,
        "Samplers": {
            "1": 6.61550967e-06,
            "2": 6.96775198e-06,
            "Bias": 0.000447273,
            "Bias Current": 0.0
        },
        "PA Performance": {
            "Gain": 9.054538581463607,
            "PAE": 10.773770983242292,
            "DC Power": 1.63386018796
        },
        "DC Parameters": {
            "gate current": 0.0,
            "gate voltage": 1.79991,
            "drain current": 0.0583534,
            "drain voltage": 27.9994
        }
    },
    "Load Point: 15.0_0j_0": {
        "load_gamma": {
            "real": 0.0,
            "imag": 0.0
        },
        "wave data": {
            "input_awave": {
                "trace_name": "input_awave_trace",
                "x": 67000000000.0,
                "y_real": [
                    0.01535966
                ],
                "y_imag": [
                    0.09762502
                ],
                "dBm_mag": [
                    -20.10258
                ]
            },
            "output_awave": {
                "trace_name": "output_awave_trace",
                "x": 67000000000.0,
                "y_real": [
                    -0.005575035
                ],
                "y_imag": [
                    -0.00116404
                ],
                "dBm_mag": [
                    -44.88972
                ]
            },
            "input_bwave": {
                "trace_name": "input_bwave_trace",
                "x": 67000000000.0,
                "y_real": [
                    -0.03949113
                ],
                "y_imag": [
                    0.2140727
                ],
                "dBm_mag": [
                    -13.24344
                ]
            },
            "output_bwave": {
                "trace_name": "output_bwave_trace",
                "x": 67000000000.0,
                "y_real": [
                    1.264592
                ],
                "y_imag": [
                    0.3449242
                ],
                "dBm_mag": [
                    2.350648
                ]
            }
        },
        "Power Meter": -56.1730635,
        "Input Power": -12.0785609324,
        "Samplers": {
            "1": 6.84860537e-06,
            "2": 6.76382075e-06,
            "Bias": 0.000466347,
            "Bias Current": 0.0
        },
        "PA Performance": {
            "Gain": 8.889036581463607,
            "PAE": 12.039472616794667,
            "DC Power": 1.75896150716
        },
        "DC Parameters": {
            "gate current": 0.0,
            "gate voltage": 1.79993,
            "drain current": 0.0628214,
            "drain voltage": 27.9994
        }
    },
    "Load Point: 16.0_0j_0": {
        "load_gamma": {
            "real": 0.0,
            "imag": 0.0
        },
        "wave data": {
            "input_awave": {
                "trace_name": "input_awave_trace",
                "x": 67000000000.0,
                "y_real": [
                    0.001674431
                ],
                "y_imag": [
                    -0.1107274
                ],
                "dBm_mag": [
                    -19.11391
                ]
            },
            "output_awave": {
                "trace_name": "output_awave_trace",
                "x": 67000000000.0,
                "y_real": [
                    0.005802902
                ],
                "y_imag": [
                    0.002306445
                ],
                "dBm_mag": [
                    -44.0901
                ]
            },
            "input_bwave": {
                "trace_name": "input_bwave_trace",
                "x": 67000000000.0,
                "y_real": [
                    0.08679419
                ],
                "y_imag": [
                    -0.2308583
                ],
                "dBm_mag": [
                    -12.15891
                ]
            },
            "output_bwave": {
                "trace_name": "output_bwave_trace",
                "x": 67000000000.0,
                "y_real": [
                    -1.301309
                ],
                "y_imag": [
                    -0.611917
                ],
                "dBm_mag": [
                    3.155187
                ]
            }
        },
        "Power Meter": -57.1675104,
        "Input Power": -11.0507916415,
        "Samplers": {
            "1": 6.8011368e-06,
            "2": 6.83324827e-06,
            "Bias": 0.000473022,
            "Bias Current": 0.0
        },
        "PA Performance": {
            "Gain": 8.70490558146361,
            "PAE": 13.32767453361807,
            "DC Power": 1.9000492975799999
        },
        "DC Parameters": {
            "gate current": 0.0,
            "gate voltage": 1.7999,
            "drain current": 0.0678606,
            "drain voltage": 27.9993
        }
    },
    "Load Point: 17.0_0j_0": {
        "load_gamma": {
            "real": 0.0,
            "imag": 0.0
        },
        "wave data": {
            "input_awave": {
                "trace_name": "input_awave_trace",
                "x": 67000000000.0,
                "y_real": [
                    -0.1240796
                ],
                "y_imag": [
                    -0.002740051
                ],
                "dBm_mag": [
                    -18.12387
                ]
            },
            "output_awave": {
                "trace_name": "output_awave_trace",
                "x": 67000000000.0,
                "y_real": [
                    0.002590778
                ],
                "y_imag": [
                    -0.006350685
                ],
                "dBm_mag": [
                    -43.27502
                ]
            },
            "input_bwave": {
                "trace_name": "input_bwave_trace",
                "x": 67000000000.0,
                "y_real": [
                    -0.2603341
                ],
                "y_imag": [
                    -0.1019359
                ],
                "dBm_mag": [
                    -11.06989
                ]
            },
            "output_bwave": {
                "trace_name": "output_bwave_trace",
                "x": 67000000000.0,
                "y_real": [
                    -0.6835475
                ],
                "y_imag": [
                    1.420915
                ],
                "dBm_mag": [
                    3.955427
                ]
            }
        },
        "Power Meter": -60.3786344,
        "Input Power": -10.0078723506,
        "Samplers": {
            "1": 6.91250752e-06,
            "2": 6.95807924e-06,
            "Bias": 0.000599861,
            "Bias Current": 0.0
        },
        "PA Performance": {
            "Gain": 8.515105581463608,
            "PAE": 14.682543723714701,
            "DC Power": 2.05925507216
        },
        "DC Parameters": {
            "gate current": 0.0,
            "gate voltage": 1.7999,
            "drain current": 0.0735464,
            "drain voltage": 27.9994
        }
    },
    "Load Point: 18.0_0j_0": {
        "load_gamma": {
            "real": 0.0,
            "imag": 0.0
        },
        "wave data": {
            "input_awave": {
                "trace_name": "input_awave_trace",
                "x": 67000000000.0,
                "y_real": [
                    0.0009093978
                ],
                "y_imag": [
                    0.1390823
                ],
                "dBm_mag": [
                    -17.13437
                ]
            },
            "output_awave": {
                "trace_name": "output_awave_trace",
                "x": 67000000000.0,
                "y_real": [
                    -0.007031702
                ],
                "y_imag": [
                    -0.002640238
                ],
                "dBm_mag": [
                    -42.486
                ]
            },
            "input_bwave": {
                "trace_name": "input_bwave_trace",
                "x": 67000000000.0,
                "y_real": [
                    -0.1090186
                ],
                "y_imag": [
                    0.297334
                ],
                "dBm_mag": [
                    -9.987313
                ]
            },
            "output_bwave": {
                "trace_name": "output_bwave_trace",
                "x": 67000000000.0,
                "y_real": [
                    1.574795
                ],
                "y_imag": [
                    0.7049375
                ],
                "dBm_mag": [
                    4.737666
                ]
            }
        },
        "Power Meter": -56.9963013,
        "Input Power": -8.95578305973,
        "Samplers": {
            "1": 6.85424053e-06,
            "2": 7.11059807e-06,
            "Bias": 0.000589371,
            "Bias Current": 0.0
        },
        "PA Performance": {
            "Gain": 8.307844581463609,
            "PAE": 16.061182993900616,
            "DC Power": 2.23597048532
        },
        "DC Parameters": {
            "gate current": 0.0,
            "gate voltage": 1.7999,
            "drain current": 0.0798578,
            "drain voltage": 27.9994
        }
    },
    "Load Point: 19.0_0j_0": {
        "load_gamma": {
            "real": 0.0,
            "imag": 0.0
        },
        "wave data": {
            "input_awave": {
                "trace_name": "input_awave_trace",
                "x": 67000000000.0,
                "y_real": [
                    0.02828943
                ],
                "y_imag": [
                    -0.1531347
                ],
                "dBm_mag": [
                    -16.15279
                ]
            },
            "output_awave": {
                "trace_name": "output_awave_trace",
                "x": 67000000000.0,
                "y_real": [
                    0.007003363
                ],
                "y_imag": [
                    0.00427366
                ],
                "dBm_mag": [
                    -41.71912
                ]
            },
            "input_bwave": {
                "trace_name": "input_bwave_trace",
                "x": 67000000000.0,
                "y_real": [
                    0.1865309
                ],
                "y_imag": [
                    -0.3059324
                ],
                "dBm_mag": [
                    -8.914742
                ]
            },
            "output_bwave": {
                "trace_name": "output_bwave_trace",
                "x": 67000000000.0,
                "y_real": [
                    -1.542967
                ],
                "y_imag": [
                    -1.080546
                ],
                "dBm_mag": [
                    5.500238
                ]
            }
        },
        "Power Meter": -60.1736078,
        "Input Power": -7.89256376886,
        "Samplers": {
            "1": 6.89232643e-06,
            "2": 7.27267878e-06,
            "Bias": 0.000557899,
            "Bias Current": 0.0
        },
        "PA Performance": {
            "Gain": 8.088836581463607,
            "PAE": 17.461302437464926,
            "DC Power": 2.42949338392
        },
        "DC Parameters": {
            "gate current": 0.0,
            "gate voltage": 1.79989,
            "drain current": 0.0867701,
            "drain voltage": 27.9992
        }
    },
    "Load Point: 20.0_0j_0": {
        "load_gamma": {
            "real": 0.0,
            "imag": 0.0
        },
        "wave data": {
            "input_awave": {
                "trace_name": "input_awave_trace",
                "x": 67000000000.0,
                "y_real": [
                    -0.1546971
                ],
                "y_imag": [
                    0.08045976
                ],
                "dBm_mag": [
                    -15.17055
                ]
            },
            "output_awave": {
                "trace_name": "output_awave_trace",
                "x": 67000000000.0,
                "y_real": [
                    -0.001020559
                ],
                "y_imag": [
                    -0.008884783
                ],
                "dBm_mag": [
                    -40.97014
                ]
            },
            "input_bwave": {
                "trace_name": "input_bwave_trace",
                "x": 67000000000.0,
                "y_real": [
                    -0.4031632
                ],
                "y_imag": [
                    0.04349788
                ],
                "dBm_mag": [
                    -7.84012
                ]
            },
            "output_bwave": {
                "trace_name": "output_bwave_trace",
                "x": 67000000000.0,
                "y_real": [
                    0.1048314
                ],
                "y_imag": [
                    2.050135
                ],
                "dBm_mag": [
                    6.246989
                ]
            }
        },
        "Power Meter": -58.0474381,
        "Input Power": -6.81379447799,
        "Samplers": {
            "1": 6.91936409e-06,
            "2": 7.38686696e-06,
            "Bias": 0.000516891,
            "Bias Current": 0.0
        },
        "PA Performance": {
            "Gain": 7.853347581463606,
            "PAE": 18.887677148750235,
            "DC Power": 2.64008302558
        },
        "DC Parameters": {
            "gate current": 0.0,
            "gate voltage": 1.79988,
            "drain current": 0.0942907,
            "drain voltage": 27.9994
        }
    },
    "Load Point: 20.25_0j_0": {
        "load_gamma": {
            "real": 0.0,
            "imag": 0.0
        },
        "wave data": {
            "input_awave": {
                "trace_name": "input_awave_trace",
                "x": 67000000000.0,
                "y_real": [
                    -0.0556787
                ],
                "y_imag": [
                    0.1719851
                ],
                "dBm_mag": [
                    -14.85731
                ]
            },
            "output_awave": {
                "trace_name": "output_awave_trace",
                "x": 67000000000.0,
                "y_real": [
                    -0.007157009
                ],
                "y_imag": [
                    -0.005764809
                ],
                "dBm_mag": [
                    -40.73371
                ]
            },
            "input_bwave": {
                "trace_name": "input_bwave_trace",
                "x": 67000000000.0,
                "y_real": [
                    -0.2675774
                ],
                "y_imag": [
                    0.3258915
                ],
                "dBm_mag": [
                    -7.500611
                ]
            },
            "output_bwave": {
                "trace_name": "output_bwave_trace",
                "x": 67000000000.0,
                "y_real": [
                    1.556213
                ],
                "y_imag": [
                    1.425177
                ],
                "dBm_mag": [
                    6.486457
                ]
            }
        },
        "Power Meter": -57.5538721,
        "Input Power": -6.46761518712,
        "Samplers": {
            "1": 7.11767726e-06,
            "2": 7.31508361e-06,
            "Bias": 0.000497818,
            "Bias Current": 0.0
        },
        "PA Performance": {
            "Gain": 7.779575581463604,
            "PAE": 19.37020381210771,
            "DC Power": 2.7111119035
        },
        "DC Parameters": {
            "gate current": 0.0,
            "gate voltage": 1.7999,
            "drain current": 0.0968275,
            "drain voltage": 27.9994
        }
    },
    "Load Point: 20.5_0j_0": {
        "load_gamma": {
            "real": 0.0,
            "imag": 0.0
        },
        "wave data": {
            "input_awave": {
                "trace_name": "input_awave_trace",
                "x": 67000000000.0,
                "y_real": [
                    -0.1765934
                ],
                "y_imag": [
                    -0.05887504
                ],
                "dBm_mag": [
                    -14.60278
                ]
            },
            "output_awave": {
                "trace_name": "output_awave_trace",
                "x": 67000000000.0,
                "y_real": [
                    0.005972748
                ],
                "y_imag": [
                    -0.007264167
                ],
                "dBm_mag": [
                    -40.53342
                ]
            },
            "input_bwave": {
                "trace_name": "input_bwave_trace",
                "x": 67000000000.0,
                "y_real": [
                    -0.3336005
                ],
                "y_imag": [
                    -0.2799759
                ],
                "dBm_mag": [
                    -7.219881
                ]
            },
            "output_bwave": {
                "trace_name": "output_bwave_trace",
                "x": 67000000000.0,
                "y_real": [
                    -1.469945
                ],
                "y_imag": [
                    1.57743
                ],
                "dBm_mag": [
                    6.67362
                ]
            }
        },
        "Power Meter": -57.7661834,
        "Input Power": -6.18265589625,
        "Samplers": {
            "1": 7.09499783e-06,
            "2": 7.18942118e-06,
            "Bias": 0.000597954,
            "Bias Current": 0.0
        },
        "PA Performance": {
            "Gain": 7.7122085814636065,
            "PAE": 19.73082136559674,
            "DC Power": 2.77007845264
        },
        "DC Parameters": {
            "gate current": 0.0,
            "gate voltage": 1.79994,
            "drain current": 0.0989342,
            "drain voltage": 27.9992
        }
    },
    "Load Point: 20.75_0j_0": {
        "load_gamma": {
            "real": 0.0,
            "imag": 0.0
        },
        "wave data": {
            "input_awave": {
                "trace_name": "input_awave_trace",
                "x": 67000000000.0,
                "y_real": [
                    0.06724928
                ],
                "y_imag": [
                    0.1793886
                ],
                "dBm_mag": [
                    -14.35302
                ]
            },
            "output_awave": {
                "trace_name": "output_awave_trace",
                "x": 67000000000.0,
                "y_real": [
                    -0.009608865
                ],
                "y_imag": [
                    -6.408655e-05
                ],
                "dBm_mag": [
                    -40.34637
                ]
            },
            "input_bwave": {
                "trace_name": "input_bwave_trace",
                "x": 67000000000.0,
                "y_real": [
                    -0.008785525
                ],
                "y_imag": [
                    0.4493477
                ],
                "dBm_mag": [
                    -6.94669
                ]
            },
            "output_bwave": {
                "trace_name": "output_bwave_trace",
                "x": 67000000000.0,
                "y_real": [
                    2.197239
                ],
                "y_imag": [
                    0.1527327
                ],
                "dBm_mag": [
                    6.858479
                ]
            }
        },
        "Power Meter": -55.6250159,
        "Input Power": -5.90171660538,
        "Samplers": {
            "1": 7.23562696e-06,
            "2": 7.31464017e-06,
            "Bias": 0.000524521,
            "Bias Current": 0.0
        },
        "PA Performance": {
            "Gain": 7.647307581463608,
            "PAE": 20.09225570260561,
            "DC Power": 2.8298231456
        },
        "DC Parameters": {
            "gate current": 0.0,
            "gate voltage": 1.79991,
            "drain current": 0.101068,
            "drain voltage": 27.9992
        }
    },
    "Load Point: 21.0_0j_0": {
        "load_gamma": {
            "real": 0.0,
            "imag": 0.0
        },
        "wave data": {
            "input_awave": {
                "trace_name": "input_awave_trace",
                "x": 67000000000.0,
                "y_real": [
                    -0.1454754
                ],
                "y_imag": [
                    -0.1330489
                ],
                "dBm_mag": [
                    -14.1044
                ]
            },
            "output_awave": {
                "trace_name": "output_awave_trace",
                "x": 67000000000.0,
                "y_real": [
                    0.008768676
                ],
                "y_imag": [
                    -0.004398937
                ],
                "dBm_mag": [
                    -40.16643
                ]
            },
            "input_bwave": {
                "trace_name": "input_bwave_trace",
                "x": 67000000000.0,
                "y_real": [
                    -0.2015559
                ],
                "y_imag": [
                    -0.4174463
                ],
                "dBm_mag": [
                    -6.677916
                ]
            },
            "output_bwave": {
                "trace_name": "output_bwave_trace",
                "x": 67000000000.0,
                "y_real": [
                    -2.069636
                ],
                "y_imag": [
                    0.8800802
                ],
                "dBm_mag": [
                    7.039731
                ]
            }
        },
        "Power Meter": -57.5025705,
        "Input Power": -5.62188731451,
        "Samplers": {
            "1": 7.31732288e-06,
            "2": 6.93338466e-06,
            "Bias": 0.000455856,
            "Bias Current": 0.0
        },
        "PA Performance": {
            "Gain": 7.579939581463606,
            "PAE": 20.44860230072477,
            "DC Power": 2.8896014376
        },
        "DC Parameters": {
            "gate current": 0.0,
            "gate voltage": 1.79994,
            "drain current": 0.103203,
            "drain voltage": 27.9992
        }
    },
    "Load Point: 21.25_0j_0": {
        "load_gamma": {
            "real": 0.0,
            "imag": 0.0
        },
        "wave data": {
            "input_awave": {
                "trace_name": "input_awave_trace",
                "x": 67000000000.0,
                "y_real": [
                    -0.1494625
                ],
                "y_imag": [
                    -0.1370502
                ],
                "dBm_mag": [
                    -13.85928
                ]
            },
            "output_awave": {
                "trace_name": "output_awave_trace",
                "x": 67000000000.0,
                "y_real": [
                    0.008962083
                ],
                "y_imag": [
                    -0.004481992
                ],
                "dBm_mag": [
                    -39.98235
                ]
            },
            "input_bwave": {
                "trace_name": "input_bwave_trace",
                "x": 67000000000.0,
                "y_real": [
                    -0.2064389
                ],
                "y_imag": [
                    -0.4310145
                ],
                "dBm_mag": [
                    -6.413219
                ]
            },
            "output_bwave": {
                "trace_name": "output_bwave_trace",
                "x": 67000000000.0,
                "y_real": [
                    -2.11408
                ],
                "y_imag": [
                    0.8963625
                ],
                "dBm_mag": [
                    7.220413
                ]
            }
        },
        "Power Meter": -62.2111462,
        "Input Power": -5.34084802364,
        "Samplers": {
            "1": 7.41095534e-06,
            "2": 6.88413408e-06,
            "Bias": 0.000557899,
            "Bias Current": 0.0
        },
        "PA Performance": {
            "Gain": 7.515501581463607,
            "PAE": 20.808347732836676,
            "DC Power": 2.9509163827
        },
        "DC Parameters": {
            "gate current": 0.0,
            "gate voltage": 1.79992,
            "drain current": 0.105391,
            "drain voltage": 27.9997
        }
    },
    "Load Point: 21.5_0j_0": {
        "load_gamma": {
            "real": 0.0,
            "imag": 0.0
        },
        "wave data": {
            "input_awave": {
                "trace_name": "input_awave_trace",
                "x": 67000000000.0,
                "y_real": [
                    0.1948333
                ],
                "y_imag": [
                    -0.07496975
                ],
                "dBm_mag": [
                    -13.60708
                ]
            },
            "output_awave": {
                "trace_name": "output_awave_trace",
                "x": 67000000000.0,
                "y_real": [
                    4.278901e-05
                ],
                "y_imag": [
                    0.01023328
                ],
                "dBm_mag": [
                    -39.79963
                ]
            },
            "input_bwave": {
                "trace_name": "input_bwave_trace",
                "x": 67000000000.0,
                "y_real": [
                    0.4932356
                ],
                "y_imag": [
                    0.008337201
                ],
                "dBm_mag": [
                    -6.13767
                ]
            },
            "output_bwave": {
                "trace_name": "output_bwave_trace",
                "x": 67000000000.0,
                "y_real": [
                    0.1407591
                ],
                "y_imag": [
                    -2.339711
                ],
                "dBm_mag": [
                    7.398933
                ]
            }
        },
        "Power Meter": -57.6175496,
        "Input Power": -5.05807873277,
        "Samplers": {
            "1": 7.42922103e-06,
            "2": 7.17373416e-06,
            "Bias": 0.000636101,
            "Bias Current": 0.0
        },
        "PA Performance": {
            "Gain": 7.441821581463607,
            "PAE": 21.15958375428641,
            "DC Power": 3.0125631645
        },
        "DC Parameters": {
            "gate current": 0.0,
            "gate voltage": 1.79992,
            "drain current": 0.107595,
            "drain voltage": 27.9991
        }
    },
    "Load Point: 21.75_0j_0": {
        "load_gamma": {
            "real": 0.0,
            "imag": 0.0
        },
        "wave data": {
            "input_awave": {
                "trace_name": "input_awave_trace",
                "x": 67000000000.0,
                "y_real": [
                    -0.006826885
                ],
                "y_imag": [
                    -0.214673
                ],
                "dBm_mag": [
                    -13.36006
                ]
            },
            "output_awave": {
                "trace_name": "output_awave_trace",
                "x": 67000000000.0,
                "y_real": [
                    0.009877377
                ],
                "y_imag": [
                    0.003390229
                ],
                "dBm_mag": [
                    -39.6235
                ]
            },
            "input_bwave": {
                "trace_name": "input_bwave_trace",
                "x": 67000000000.0,
                "y_real": [
                    0.1764648
                ],
                "y_imag": [
                    -0.4771727
                ],
                "dBm_mag": [
                    -5.869793
                ]
            },
            "output_bwave": {
                "trace_name": "output_bwave_trace",
                "x": 67000000000.0,
                "y_real": [
                    -2.207263
                ],
                "y_imag": [
                    -0.921173
                ],
                "dBm_mag": [
                    7.574391
                ]
            }
        },
        "Power Meter": -57.6774291,
        "Input Power": -4.7748994419,
        "Samplers": {
            "1": 7.16839369e-06,
            "2": 7.18897773e-06,
            "Bias": 0.000638008,
            "Bias Current": 0.0
        },
        "PA Performance": {
            "Gain": 7.3702595814636105,
            "PAE": 21.501561141937085,
            "DC Power": 3.0756001231999996
        },
        "DC Parameters": {
            "gate current": 0.0,
            "gate voltage": 1.79991,
            "drain current": 0.109846,
            "drain voltage": 27.9992
        }
    },
    "Load Point: 22.0_0j_0": {
        "load_gamma": {
            "real": 0.0,
            "imag": 0.0
        },
        "wave data": {
            "input_awave": {
                "trace_name": "input_awave_trace",
                "x": 67000000000.0,
                "y_real": [
                    0.1146604
                ],
                "y_imag": [
                    -0.18896
                ],
                "dBm_mag": [
                    -13.1111
                ]
            },
            "output_awave": {
                "trace_name": "output_awave_trace",
                "x": 67000000000.0,
                "y_real": [
                    0.006564817
                ],
                "y_imag": [
                    0.008380166
                ],
                "dBm_mag": [
                    -39.45678
                ]
            },
            "input_bwave": {
                "trace_name": "input_bwave_trace",
                "x": 67000000000.0,
                "y_real": [
                    0.4217231
                ],
                "y_imag": [
                    -0.3123656
                ],
                "dBm_mag": [
                    -5.600004
                ]
            },
            "output_bwave": {
                "trace_name": "output_bwave_trace",
                "x": 67000000000.0,
                "y_real": [
                    -1.375761
                ],
                "y_imag": [
                    -2.016736
                ],
                "dBm_mag": [
                    7.75242
                ]
            }
        },
        "Power Meter": -54.833582,
        "Input Power": -4.48849015103,
        "Samplers": {
            "1": 7.14229985e-06,
            "2": 7.50055627e-06,
            "Bias": 0.000612259,
            "Bias Current": 0.0
        },
        "PA Performance": {
            "Gain": 7.299328581463609,
            "PAE": 21.860182875772875,
            "DC Power": 3.140087926
        },
        "DC Parameters": {
            "gate current": 0.0,
            "gate voltage": 1.79993,
            "drain current": 0.112148,
            "drain voltage": 27.9995
        }
    },
    "Load Point: 22.25_0j_0": {
        "load_gamma": {
            "real": 0.0,
            "imag": 0.0
        },
        "wave data": {
            "input_awave": {
                "trace_name": "input_awave_trace",
                "x": 67000000000.0,
                "y_real": [
                    0.1305348
                ],
                "y_imag": [
                    -0.1862583
                ],
                "dBm_mag": [
                    -12.86245
                ]
            },
            "output_awave": {
                "trace_name": "output_awave_trace",
                "x": 67000000000.0,
                "y_real": [
                    0.006120833
                ],
                "y_imag": [
                    0.008953936
                ],
                "dBm_mag": [
                    -39.29454
                ]
            },
            "input_bwave": {
                "trace_name": "input_bwave_trace",
                "x": 67000000000.0,
                "y_real": [
                    0.4559301
                ],
                "y_imag": [
                    -0.2920336
                ],
                "dBm_mag": [
                    -5.329014
                ]
            },
            "output_bwave": {
                "trace_name": "output_bwave_trace",
                "x": 67000000000.0,
                "y_real": [
                    -1.265223
                ],
                "y_imag": [
                    -2.144204
                ],
                "dBm_mag": [
                    7.922796
                ]
            }
        },
        "Power Meter": -59.2318695,
        "Input Power": -4.20030086016,
        "Samplers": {
            "1": 7.18066334e-06,
            "2": 7.11137411e-06,
            "Bias": 0.000589371,
            "Bias Current": 0.0
        },
        "PA Performance": {
            "Gain": 7.221054581463612,
            "PAE": 22.177606183298362,
            "DC Power": 3.2055838584000003
        },
        "DC Parameters": {
            "gate current": 0.0,
            "gate voltage": 1.79989,
            "drain current": 0.114488,
            "drain voltage": 27.9993
        }
    },
    "Load Point: 22.5_0j_0": {
        "load_gamma": {
            "real": 0.0,
            "imag": 0.0
        },
        "wave data": {
            "input_awave": {
                "trace_name": "input_awave_trace",
                "x": 67000000000.0,
                "y_real": [
                    0.2172651
                ],
                "y_imag": [
                    -0.08695728
                ],
                "dBm_mag": [
                    -12.61491
                ]
            },
            "output_awave": {
                "trace_name": "output_awave_trace",
                "x": 67000000000.0,
                "y_real": [
                    0.0002419243
                ],
                "y_imag": [
                    0.0110521
                ],
                "dBm_mag": [
                    -39.12902
                ]
            },
            "input_bwave": {
                "trace_name": "input_bwave_trace",
                "x": 67000000000.0,
                "y_real": [
                    0.5583843
                ],
                "y_imag": [
                    0.006140532
                ],
                "dBm_mag": [
                    -5.060811
                ]
            },
            "output_bwave": {
                "trace_name": "output_bwave_trace",
                "x": 67000000000.0,
                "y_real": [
                    0.1145858
                ],
                "y_imag": [
                    -2.536908
                ],
                "dBm_mag": [
                    8.094947
                ]
            }
        },
        "Power Meter": -56.6793783,
        "Input Power": -3.91056156929,
        "Samplers": {
            "1": 7.17069772e-06,
            "2": 7.16893937e-06,
            "Bias": 0.000566483,
            "Bias Current": 0.0
        },
        "PA Performance": {
            "Gain": 7.145665581463611,
            "PAE": 22.513381278740408,
            "DC Power": 3.2719981980000004
        },
        "DC Parameters": {
            "gate current": 0.0,
            "gate voltage": 1.7999,
            "drain current": 0.11686,
            "drain voltage": 27.9993
        }
    },
    "Load Point: 22.75_0j_0": {
        "load_gamma": {
            "real": 0.0,
            "imag": 0.0
        },
        "wave data": {
            "input_awave": {
                "trace_name": "input_awave_trace",
                "x": 67000000000.0,
                "y_real": [
                    0.2126231
                ],
                "y_imag": [
                    0.1129178
                ],
                "dBm_mag": [
                    -12.36879
                ]
            },
            "output_awave": {
                "trace_name": "output_awave_trace",
                "x": 67000000000.0,
                "y_real": [
                    -0.008435085
                ],
                "y_imag": [
                    0.007465571
                ],
                "dBm_mag": [
                    -38.96588
                ]
            },
            "input_bwave": {
                "trace_name": "input_bwave_trace",
                "x": 67000000000.0,
                "y_real": [
                    0.3660997
                ],
                "y_imag": [
                    0.4444011
                ],
                "dBm_mag": [
                    -4.794886
                ]
            },
            "output_bwave": {
                "trace_name": "output_bwave_trace",
                "x": 67000000000.0,
                "y_real": [
                    2.049508
                ],
                "y_imag": [
                    -1.582114
                ],
                "dBm_mag": [
                    8.263061
                ]
            }
        },
        "Power Meter": -55.3669937,
        "Input Power": -3.62087227842,
        "Samplers": {
            "1": 7.44398903e-06,
            "2": 7.22910989e-06,
            "Bias": 0.000508308,
            "Bias Current": 0.0
        },
        "PA Performance": {
            "Gain": 7.067659581463609,
            "PAE": 22.83318458721237,
            "DC Power": 3.3389725236000003
        },
        "DC Parameters": {
            "gate current": 0.0,
            "gate voltage": 1.79991,
            "drain current": 0.119252,
            "drain voltage": 27.9993
        }
    },
    "Load Point: 23.0_0j_0": {
        "load_gamma": {
            "real": 0.0,
            "imag": 0.0
        },
        "wave data": {
            "input_awave": {
                "trace_name": "input_awave_trace",
                "x": 67000000000.0,
                "y_real": [
                    -0.2330023
                ],
                "y_imag": [
                    -0.08427552
                ],
                "dBm_mag": [
                    -12.11885
                ]
            },
            "output_awave": {
                "trace_name": "output_awave_trace",
                "x": 67000000000.0,
                "y_real": [
                    0.007435353
                ],
                "y_imag": [
                    -0.008750466
                ],
                "dBm_mag": [
                    -38.79903
                ]
            },
            "input_bwave": {
                "trace_name": "input_bwave_trace",
                "x": 67000000000.0,
                "y_real": [
                    -0.4375513
                ],
                "y_imag": [
                    -0.4015079
                ],
                "dBm_mag": [
                    -4.526441
                ]
            },
            "output_bwave": {
                "trace_name": "output_bwave_trace",
                "x": 67000000000.0,
                "y_real": [
                    -1.84032
                ],
                "y_imag": [
                    1.892369
                ],
                "dBm_mag": [
                    8.430982
                ]
            }
        },
        "Power Meter": -58.0246048,
        "Input Power": -3.32508298755,
        "Samplers": {
            "1": 7.53817668e-06,
            "2": 7.34861946e-06,
            "Bias": 0.000610352,
            "Bias Current": 0.0
        },
        "PA Performance": {
            "Gain": 6.98564058146361,
            "PAE": 23.143057376885753,
            "DC Power": 3.4081746207999997
        },
        "DC Parameters": {
            "gate current": 0.0,
            "gate voltage": 1.79992,
            "drain current": 0.121724,
            "drain voltage": 27.9992
        }
    },
    "Load Point: 23.25_0j_0": {
        "load_gamma": {
            "real": 0.0,
            "imag": 0.0
        },
        "wave data": {
            "input_awave": {
                "trace_name": "input_awave_trace",
                "x": 67000000000.0,
                "y_real": [
                    -0.2377676
                ],
                "y_imag": [
                    -0.09197079
                ],
                "dBm_mag": [
                    -11.8714
                ]
            },
            "output_awave": {
                "trace_name": "output_awave_trace",
                "x": 67000000000.0,
                "y_real": [
                    0.00776922
                ],
                "y_imag": [
                    -0.008743246
                ],
                "dBm_mag": [
                    -38.63898
                ]
            },
            "input_bwave": {
                "trace_name": "input_bwave_trace",
                "x": 67000000000.0,
                "y_real": [
                    -0.4411759
                ],
                "y_imag": [
                    -0.4247977
                ],
                "dBm_mag": [
                    -4.258653
                ]
            },
            "output_bwave": {
                "trace_name": "output_bwave_trace",
                "x": 67000000000.0,
                "y_real": [
                    -1.916164
                ],
                "y_imag": [
                    1.886929
                ],
                "dBm_mag": [
                    8.592694
                ]
            }
        },
        "Power Meter": -61.1005661,
        "Input Power": -3.03057369668,
        "Samplers": {
            "1": 7.46339285e-06,
            "2": 7.18218741e-06,
            "Bias": 0.000499725,
            "Bias Current": 0.0
        },
        "PA Performance": {
            "Gain": 6.899902581463607,
            "PAE": 23.42598873067455,
            "DC Power": 3.477307806
        },
        "DC Parameters": {
            "gate current": 0.0,
            "gate voltage": 1.79992,
            "drain current": 0.124194,
            "drain voltage": 27.999
        }
    },
    "Load Point: 23.5_0j_0": {
        "load_gamma": {
            "real": 0.0,
            "imag": 0.0
        },
        "wave data": {
            "input_awave": {
                "trace_name": "input_awave_trace",
                "x": 67000000000.0,
                "y_real": [
                    0.08808239
                ],
                "y_imag": [
                    -0.2470024
                ],
                "dBm_mag": [
                    -11.62609
                ]
            },
            "output_awave": {
                "trace_name": "output_awave_trace",
                "x": 67000000000.0,
                "y_real": [
                    0.009126366
                ],
                "y_imag": [
                    0.007656605
                ],
                "dBm_mag": [
                    -38.47974
                ]
            },
            "input_bwave": {
                "trace_name": "input_bwave_trace",
                "x": 67000000000.0,
                "y_real": [
                    0.4266711
                ],
                "y_imag": [
                    -0.4654863
                ],
                "dBm_mag": [
                    -3.993258
                ]
            },
            "output_bwave": {
                "trace_name": "output_bwave_trace",
                "x": 67000000000.0,
                "y_real": [
                    -1.974674
                ],
                "y_imag": [
                    -1.898725
                ],
                "dBm_mag": [
                    8.753213
                ]
            }
        },
        "Power Meter": -57.6103235,
        "Input Power": -2.73257440581,
        "Samplers": {
            "1": 7.48263012e-06,
            "2": 7.35856936e-06,
            "Bias": 0.000596046,
            "Bias Current": 0.0
        },
        "PA Performance": {
            "Gain": 6.815111581463604,
            "PAE": 23.704576579498504,
            "DC Power": 3.5477939600999995
        },
        "DC Parameters": {
            "gate current": 0.0,
            "gate voltage": 1.79991,
            "drain current": 0.126711,
            "drain voltage": 27.9991
        }
    },
    "Load Point: 23.75_0j_0": {
        "load_gamma": {
            "real": 0.0,
            "imag": 0.0
        },
        "wave data": {
            "input_awave": {
                "trace_name": "input_awave_trace",
                "x": 67000000000.0,
                "y_real": [
                    -0.08570077
                ],
                "y_imag": [
                    -0.2558619
                ],
                "dBm_mag": [
                    -11.37809
                ]
            },
            "output_awave": {
                "trace_name": "output_awave_trace",
                "x": 67000000000.0,
                "y_real": [
                    0.01212656
                ],
                "y_imag": [
                    0.0003769147
                ],
                "dBm_mag": [
                    -38.32105
                ]
            },
            "input_bwave": {
                "trace_name": "input_bwave_trace",
                "x": 67000000000.0,
                "y_real": [
                    0.05075764
                ],
                "y_imag": [
                    -0.6491037
                ],
                "dBm_mag": [
                    -3.727243
                ]
            },
            "output_bwave": {
                "trace_name": "output_bwave_trace",
                "x": 67000000000.0,
                "y_real": [
                    -2.777193
                ],
                "y_imag": [
                    -0.2765618
                ],
                "dBm_mag": [
                    8.914978
                ]
            }
        },
        "Power Meter": -58.3274539,
        "Input Power": -2.43040511494,
        "Samplers": {
            "1": 7.3748126e-06,
            "2": 7.55740092e-06,
            "Bias": 0.000608444,
            "Bias Current": 0.0
        },
        "PA Performance": {
            "Gain": 6.728876581463609,
            "PAE": 23.99299997977096,
            "DC Power": 3.6189805976
        },
        "DC Parameters": {
            "gate current": 0.0,
            "gate voltage": 1.79993,
            "drain current": 0.129253,
            "drain voltage": 27.9992
        }
    },
    "Load Point: 24.0_0j_0": {
        "load_gamma": {
            "real": 0.0,
            "imag": 0.0
        },
        "wave data": {
            "input_awave": {
                "trace_name": "input_awave_trace",
                "x": 67000000000.0,
                "y_real": [
                    -0.2432698
                ],
                "y_imag": [
                    0.1339036
                ],
                "dBm_mag": [
                    -11.12887
                ]
            },
            "output_awave": {
                "trace_name": "output_awave_trace",
                "x": 67000000000.0,
                "y_real": [
                    -0.001841921
                ],
                "y_imag": [
                    -0.01222674
                ],
                "dBm_mag": [
                    -38.15633
                ]
            },
            "input_bwave": {
                "trace_name": "input_bwave_trace",
                "x": 67000000000.0,
                "y_real": [
                    -0.6682416
                ],
                "y_imag": [
                    0.0671639
                ],
                "dBm_mag": [
                    -3.457678
                ]
            },
            "output_bwave": {
                "trace_name": "output_bwave_trace",
                "x": 67000000000.0,
                "y_real": [
                    0.2301818
                ],
                "y_imag": [
                    2.832154
                ],
                "dBm_mag": [
                    9.07093
                ]
            }
        },
        "Power Meter": -55.6506876,
        "Input Power": -2.12390582407,
        "Samplers": {
            "1": 7.50525403e-06,
            "2": 7.14643432e-06,
            "Bias": 0.00056076,
            "Bias Current": 0.0
        },
        "PA Performance": {
            "Gain": 6.635608581463607,
            "PAE": 24.2345433239994,
            "DC Power": 3.6921688804000006
        },
        "DC Parameters": {
            "gate current": 0.0,
            "gate voltage": 1.79991,
            "drain current": 0.131866,
            "drain voltage": 27.9994
        }
    },
    "Load Point: 24.25_0j_0": {
        "load_gamma": {
            "real": 0.0,
            "imag": 0.0
        },
        "wave data": {
            "input_awave": {
                "trace_name": "input_awave_trace",
                "x": 67000000000.0,
                "y_real": [
                    0.2025671
                ],
                "y_imag": [
                    -0.2012338
                ],
                "dBm_mag": [
                    -10.88691
                ]
            },
            "output_awave": {
                "trace_name": "output_awave_trace",
                "x": 67000000000.0,
                "y_real": [
                    0.005244779
                ],
                "y_imag": [
                    0.01144683
                ],
                "dBm_mag": [
                    -37.99868
                ]
            },
            "input_bwave": {
                "trace_name": "input_bwave_trace",
                "x": 67000000000.0,
                "y_real": [
                    0.6433485
                ],
                "y_imag": [
                    -0.254914
                ],
                "dBm_mag": [
                    -3.197748
                ]
            },
            "output_bwave": {
                "trace_name": "output_bwave_trace",
                "x": 67000000000.0,
                "y_real": [
                    -1.021343
                ],
                "y_imag": [
                    -2.704591
                ],
                "dBm_mag": [
                    9.221001
                ]
            }
        },
        "Power Meter": -58.9567061,
        "Input Power": -1.8174665332,
        "Samplers": {
            "1": 7.60846349e-06,
            "2": 6.98199779e-06,
            "Bias": 0.000599861,
            "Bias Current": 0.0
        },
        "PA Performance": {
            "Gain": 6.5437195814636056,
            "PAE": 24.45875131151435,
            "DC Power": 3.7645058849999997
        },
        "DC Parameters": {
            "gate current": 0.0,
            "gate voltage": 1.79992,
            "drain current": 0.13445,
            "drain voltage": 27.9993
        }
    },
    "Load Point: 24.5_0j_0": {
        "load_gamma": {
            "real": 0.0,
            "imag": 0.0
        },
        "wave data": {
            "input_awave": {
                "trace_name": "input_awave_trace",
                "x": 67000000000.0,
                "y_real": [
                    -0.04314407
                ],
                "y_imag": [
                    0.2906064
                ],
                "dBm_mag": [
                    -10.63921
                ]
            },
            "output_awave": {
                "trace_name": "output_awave_trace",
                "x": 67000000000.0,
                "y_real": [
                    -0.01126883
                ],
                "y_imag": [
                    -0.006142609
                ],
                "dBm_mag": [
                    -37.83259
                ]
            },
            "input_bwave": {
                "trace_name": "input_bwave_trace",
                "x": 67000000000.0,
                "y_real": [
                    -0.3755075
                ],
                "y_imag": [
                    0.6069388
                ],
                "dBm_mag": [
                    -2.929576
                ]
            },
            "output_bwave": {
                "trace_name": "output_bwave_trace",
                "x": 67000000000.0,
                "y_real": [
                    2.480425
                ],
                "y_imag": [
                    1.580921
                ],
                "dBm_mag": [
                    9.371075
                ]
            }
        },
        "Power Meter": -56.5069296,
        "Input Power": -1.50640724233,
        "Samplers": {
            "1": 7.26283117e-06,
            "2": 7.39875695e-06,
            "Bias": 0.000696182,
            "Bias Current": 0.0
        },
        "PA Performance": {
            "Gain": 6.446093581463607,
            "PAE": 24.674007819145796,
            "DC Power": 3.837864051
        },
        "DC Parameters": {
            "gate current": 0.0,
            "gate voltage": 1.79992,
            "drain current": 0.13707,
            "drain voltage": 27.9993
        }
    },
    "Load Point: 24.75_0j_0": {
        "load_gamma": {
            "real": 0.0,
            "imag": 0.0
        },
        "wave data": {
            "input_awave": {
                "trace_name": "input_awave_trace",
                "x": 67000000000.0,
                "y_real": [
                    0.03722854
                ],
                "y_imag": [
                    0.2998907
                ],
                "dBm_mag": [
                    -10.39432
                ]
            },
            "output_awave": {
                "trace_name": "output_awave_trace",
                "x": 67000000000.0,
                "y_real": [
                    -0.01271745
                ],
                "y_imag": [
                    -0.002934759
                ],
                "dBm_mag": [
                    -37.68667
                ]
            },
            "input_bwave": {
                "trace_name": "input_bwave_trace",
                "x": 67000000000.0,
                "y_real": [
                    -0.2069239
                ],
                "y_imag": [
                    0.7058297
                ],
                "dBm_mag": [
                    -2.667922
                ]
            },
            "output_bwave": {
                "trace_name": "output_bwave_trace",
                "x": 67000000000.0,
                "y_real": [
                    2.861786
                ],
                "y_imag": [
                    0.8704123
                ],
                "dBm_mag": [
                    9.516985
                ]
            }
        },
        "Power Meter": -54.7496023,
        "Input Power": -1.18992795146,
        "Samplers": {
            "1": 7.53245824e-06,
            "2": 7.03438023e-06,
            "Bias": 0.000589371,
            "Bias Current": 0.0
        },
        "PA Performance": {
            "Gain": 6.34711358146361,
            "PAE": 24.863237098491442,
            "DC Power": 3.9121741385000006
        },
        "DC Parameters": {
            "gate current": 0.0,
            "gate voltage": 1.79994,
            "drain current": 0.139723,
            "drain voltage": 27.9995
        }
    },
    "Load Point: 25.0_0j_0": {
        "load_gamma": {
            "real": 0.0,
            "imag": 0.0
        },
        "wave data": {
            "input_awave": {
                "trace_name": "input_awave_trace",
                "x": 67000000000.0,
                "y_real": [
                    -0.3086498
                ],
                "y_imag": [
                    0.03652431
                ],
                "dBm_mag": [
                    -10.15029
                ]
            },
            "output_awave": {
                "trace_name": "output_awave_trace",
                "x": 67000000000.0,
                "y_real": [
                    0.00307155
                ],
                "y_imag": [
                    -0.01292804
                ],
                "dBm_mag": [
                    -37.53086
                ]
            },
            "input_bwave": {
                "trace_name": "input_bwave_trace",
                "x": 67000000000.0,
                "y_real": [
                    -0.7257699
                ],
                "y_imag": [
                    -0.2186833
                ],
                "dBm_mag": [
                    -2.406613
                ]
            },
            "output_bwave": {
                "trace_name": "output_bwave_trace",
                "x": 67000000000.0,
                "y_real": [
                    -0.8985352
                ],
                "y_imag": [
                    2.90537
                ],
                "dBm_mag": [
                    9.66073
                ]
            }
        },
        "Power Meter": -58.4470504,
        "Input Power": -0.869218660591,
        "Samplers": {
            "1": 7.37975377e-06,
            "2": 6.97922623e-06,
            "Bias": 0.000512123,
            "Bias Current": 0.0
        },
        "PA Performance": {
            "Gain": 6.246828581463603,
            "PAE": 25.04187110691899,
            "DC Power": 3.986666092
        },
        "DC Parameters": {
            "gate current": 0.0,
            "gate voltage": 1.79991,
            "drain current": 0.142385,
            "drain voltage": 27.9992
        }
    }
}